zzzutils/__init__.py
zzzutils/zzzutils.py
zzzutils-0.1.7.dist-info/DESCRIPTION.rst
zzzutils-0.1.7.dist-info/LICENSE.txt
zzzutils-0.1.7.dist-info/METADATA
zzzutils-0.1.7.dist-info/RECORD
zzzutils-0.1.7.dist-info/WHEEL
zzzutils-0.1.7.dist-info/metadata.json
zzzutils-0.1.7.dist-info/top_level.txt
